servo_adapter/__init__.py
servo_adapter/py.typed
servo_adapter-0.0.3.dist-info/METADATA
servo_adapter-0.0.3.dist-info/WHEEL
servo_adapter-0.0.3.dist-info/licenses/LICENSE
servo_adapter-0.0.3.dist-info/RECORD
